<?xml version="1.0" encoding="utf-8"?>
<fox formatVersion="2" fileVersion="0">
  <classes>
    <class name="Entity" super="" version="2" />
    <class name="Data" super="Entity" version="2" />
    <class name="DataSet" super="" version="0" />
    <class name="TppLandingZoneData" super="" version="1" />
    <class name="TransformEntity" super="" version="0" />
    <class name="TexturePackLoadConditioner" super="" version="0" />
  </classes>
  <entities>
    <entity class="DataSet" classVersion="0" addr="0x07CDD050" unknown1="232" unknown2="329251">
      <staticProperties>
        <property name="name" type="String" container="StaticArray" arraySize="1">
          <value hash="0xB8A0BF169F98" />
        </property>
        <property name="dataSet" type="EntityHandle" container="StaticArray" arraySize="1">
          <value>0x00000000</value>
        </property>
        <property name="dataList" type="EntityPtr" container="StringMap" arraySize="8">
          <value key="lz_enemyBase_S0000|lz_enemyBase_S_0000">0x0851C4F0</value>
          <value key="lz_remnantsNorth_N0000|lz_remnantsNorth_N_0000">0x04DD9230</value>
          <value key="lz_tent_E0000|lz_tent_E_0000">0x04DD95B0</value>
          <value key="lz_enemyBase_I0000|lz_enemyBase_I_0000">0x056B2700</value>
          <value key="lz_tent_I0000|lz_tent_I_0000">0x056BBD10</value>
          <value key="lz_remnants_I0000|lz_remnants_I_0000">0x07BC5020</value>
          <value key="lz_tent_N0000|lz_tent_N_0000">0x082598C0</value>
          <value key="TexturePackLoadConditioner0000">0x03FF5560</value>
        </property>
      </staticProperties>
      <dynamicProperties />
    </entity>
    <entity class="TppLandingZoneData" classVersion="1" addr="0x0851C4F0" unknown1="272" unknown2="40335978">
      <staticProperties>
        <property name="name" type="String" container="StaticArray" arraySize="1">
          <value>lz_enemyBase_S0000|lz_enemyBase_S_0000</value>
        </property>
        <property name="dataSet" type="EntityHandle" container="StaticArray" arraySize="1">
          <value>0x07CDD050</value>
        </property>
        <property name="parent" type="EntityHandle" container="StaticArray" arraySize="1">
          <value>0x00000000</value>
        </property>
        <property name="transform" type="EntityPtr" container="StaticArray" arraySize="1">
          <value>0x0851C560</value>
        </property>
        <property name="shearTransform" type="EntityPtr" container="StaticArray" arraySize="1">
          <value>0x00000000</value>
        </property>
        <property name="pivotTransform" type="EntityPtr" container="StaticArray" arraySize="1">
          <value>0x00000000</value>
        </property>
        <property name="children" type="EntityHandle" container="List" />
        <property name="flags" type="uint32" container="StaticArray" arraySize="1">
          <value>7</value>
        </property>
        <property name="approachRoute" type="String" container="StaticArray" arraySize="1">
          <value>lz_enemyBase_S0000|rt_apr_enemyBase_S_0000</value>
        </property>
        <property name="returnRoute" type="String" container="StaticArray" arraySize="1">
          <value>lz_enemyBase_S0000|rt_rtn_enemyBase_S_0000</value>
        </property>
      </staticProperties>
      <dynamicProperties />
    </entity>
    <entity class="TransformEntity" classVersion="0" addr="0x0851C560" unknown1="80" unknown2="40335981">
      <staticProperties>
        <property name="owner" type="EntityHandle" container="StaticArray" arraySize="1">
          <value>0x0851C4F0</value>
        </property>
        <property name="transform_scale" type="Vector3" container="StaticArray" arraySize="1">
          <value x="0.9999991" y="1" z="0.9999991" w="1.121039E-44" />
        </property>
        <property name="transform_rotation_quat" type="Quat" container="StaticArray" arraySize="1">
          <value x="0" y="0.499998778" z="0" w="0.8660261" />
        </property>
        <property name="transform_translation" type="Vector3" container="StaticArray" arraySize="1">
          <value x="-351.612" y="315.219055" z="768.338" w="1" />
        </property>
      </staticProperties>
      <dynamicProperties />
    </entity>
    <entity class="TppLandingZoneData" classVersion="1" addr="0x04DD9230" unknown1="272" unknown2="37825370">
      <staticProperties>
        <property name="name" type="String" container="StaticArray" arraySize="1">
          <value>lz_remnantsNorth_N0000|lz_remnantsNorth_N_0000</value>
        </property>
        <property name="dataSet" type="EntityHandle" container="StaticArray" arraySize="1">
          <value>0x07CDD050</value>
        </property>
        <property name="parent" type="EntityHandle" container="StaticArray" arraySize="1">
          <value>0x00000000</value>
        </property>
        <property name="transform" type="EntityPtr" container="StaticArray" arraySize="1">
          <value>0x04DD92A0</value>
        </property>
        <property name="shearTransform" type="EntityPtr" container="StaticArray" arraySize="1">
          <value>0x00000000</value>
        </property>
        <property name="pivotTransform" type="EntityPtr" container="StaticArray" arraySize="1">
          <value>0x00000000</value>
        </property>
        <property name="children" type="EntityHandle" container="List" />
        <property name="flags" type="uint32" container="StaticArray" arraySize="1">
          <value>7</value>
        </property>
        <property name="approachRoute" type="String" container="StaticArray" arraySize="1">
          <value>lz_remnantsNorth_N0000|rt_apr_remnantsNorth_N_0000</value>
        </property>
        <property name="returnRoute" type="String" container="StaticArray" arraySize="1">
          <value>lz_remnantsNorth_N0000|rt_rtn_remnantsNorth_N_0000</value>
        </property>
      </staticProperties>
      <dynamicProperties />
    </entity>
    <entity class="TransformEntity" classVersion="0" addr="0x04DD92A0" unknown1="80" unknown2="37825373">
      <staticProperties>
        <property name="owner" type="EntityHandle" container="StaticArray" arraySize="1">
          <value>0x04DD9230</value>
        </property>
        <property name="transform_scale" type="Vector3" container="StaticArray" arraySize="1">
          <value x="0.999999344" y="1" z="0.999999344" w="1.121039E-44" />
        </property>
        <property name="transform_rotation_quat" type="Quat" container="StaticArray" arraySize="1">
          <value x="0" y="0.382678121" z="0" w="0.9238817" />
        </property>
        <property name="transform_translation" type="Vector3" container="StaticArray" arraySize="1">
          <value x="-836.857" y="281.8926" z="1574.066" w="1" />
        </property>
      </staticProperties>
      <dynamicProperties />
    </entity>
    <entity class="TppLandingZoneData" classVersion="1" addr="0x04DD95B0" unknown1="272" unknown2="115624">
      <staticProperties>
        <property name="name" type="String" container="StaticArray" arraySize="1">
          <value>lz_tent_E0000|lz_tent_E_0000</value>
        </property>
        <property name="dataSet" type="EntityHandle" container="StaticArray" arraySize="1">
          <value>0x07CDD050</value>
        </property>
        <property name="parent" type="EntityHandle" container="StaticArray" arraySize="1">
          <value>0x00000000</value>
        </property>
        <property name="transform" type="EntityPtr" container="StaticArray" arraySize="1">
          <value>0x04DD9620</value>
        </property>
        <property name="shearTransform" type="EntityPtr" container="StaticArray" arraySize="1">
          <value>0x00000000</value>
        </property>
        <property name="pivotTransform" type="EntityPtr" container="StaticArray" arraySize="1">
          <value>0x00000000</value>
        </property>
        <property name="children" type="EntityHandle" container="List" />
        <property name="flags" type="uint32" container="StaticArray" arraySize="1">
          <value>7</value>
        </property>
        <property name="approachRoute" type="String" container="StaticArray" arraySize="1">
          <value>lz_tent_E0000|rt_apr_tent_E_0000</value>
        </property>
        <property name="returnRoute" type="String" container="StaticArray" arraySize="1">
          <value>lz_tent_E0000|rt_rtn_tent_E_0000</value>
        </property>
      </staticProperties>
      <dynamicProperties />
    </entity>
    <entity class="TransformEntity" classVersion="0" addr="0x04DD9620" unknown1="80" unknown2="115627">
      <staticProperties>
        <property name="owner" type="EntityHandle" container="StaticArray" arraySize="1">
          <value>0x04DD95B0</value>
        </property>
        <property name="transform_scale" type="Vector3" container="StaticArray" arraySize="1">
          <value x="0.99999994" y="1" z="0.99999994" w="1.121039E-44" />
        </property>
        <property name="transform_rotation_quat" type="Quat" container="StaticArray" arraySize="1">
          <value x="0" y="-0.608762145" z="0" w="0.7933528" />
        </property>
        <property name="transform_translation" type="Vector3" container="StaticArray" arraySize="1">
          <value x="-1372.17981" y="311.330536" z="934.6754" w="1" />
        </property>
      </staticProperties>
      <dynamicProperties />
    </entity>
    <entity class="TppLandingZoneData" classVersion="1" addr="0x056B2700" unknown1="272" unknown2="948412">
      <staticProperties>
        <property name="name" type="String" container="StaticArray" arraySize="1">
          <value>lz_enemyBase_I0000|lz_enemyBase_I_0000</value>
        </property>
        <property name="dataSet" type="EntityHandle" container="StaticArray" arraySize="1">
          <value>0x07CDD050</value>
        </property>
        <property name="parent" type="EntityHandle" container="StaticArray" arraySize="1">
          <value>0x00000000</value>
        </property>
        <property name="transform" type="EntityPtr" container="StaticArray" arraySize="1">
          <value>0x056B2770</value>
        </property>
        <property name="shearTransform" type="EntityPtr" container="StaticArray" arraySize="1">
          <value>0x00000000</value>
        </property>
        <property name="pivotTransform" type="EntityPtr" container="StaticArray" arraySize="1">
          <value>0x00000000</value>
        </property>
        <property name="children" type="EntityHandle" container="List" />
        <property name="flags" type="uint32" container="StaticArray" arraySize="1">
          <value>7</value>
        </property>
        <property name="approachRoute" type="String" container="StaticArray" arraySize="1">
          <value>lz_enemyBase_I0000|rt_apr_enemyBase_I_0000</value>
        </property>
        <property name="returnRoute" type="String" container="StaticArray" arraySize="1">
          <value>lz_enemyBase_I0000|rt_rtn_enemyBase_I_0000</value>
        </property>
      </staticProperties>
      <dynamicProperties />
    </entity>
    <entity class="TransformEntity" classVersion="0" addr="0x056B2770" unknown1="80" unknown2="948415">
      <staticProperties>
        <property name="owner" type="EntityHandle" container="StaticArray" arraySize="1">
          <value>0x056B2700</value>
        </property>
        <property name="transform_scale" type="Vector3" container="StaticArray" arraySize="1">
          <value x="1" y="1" z="1" w="1.121039E-44" />
        </property>
        <property name="transform_rotation_quat" type="Quat" container="StaticArray" arraySize="1">
          <value x="0" y="1" z="0" w="5E-06" />
        </property>
        <property name="transform_translation" type="Vector3" container="StaticArray" arraySize="1">
          <value x="-596.887" y="346.19574" z="497.3986" w="1" />
        </property>
      </staticProperties>
      <dynamicProperties />
    </entity>
    <entity class="TppLandingZoneData" classVersion="1" addr="0x056BBD10" unknown1="272" unknown2="386862">
      <staticProperties>
        <property name="name" type="String" container="StaticArray" arraySize="1">
          <value>lz_tent_I0000|lz_tent_I_0000</value>
        </property>
        <property name="dataSet" type="EntityHandle" container="StaticArray" arraySize="1">
          <value>0x07CDD050</value>
        </property>
        <property name="parent" type="EntityHandle" container="StaticArray" arraySize="1">
          <value>0x00000000</value>
        </property>
        <property name="transform" type="EntityPtr" container="StaticArray" arraySize="1">
          <value>0x056BBD80</value>
        </property>
        <property name="shearTransform" type="EntityPtr" container="StaticArray" arraySize="1">
          <value>0x00000000</value>
        </property>
        <property name="pivotTransform" type="EntityPtr" container="StaticArray" arraySize="1">
          <value>0x00000000</value>
        </property>
        <property name="children" type="EntityHandle" container="List" />
        <property name="flags" type="uint32" container="StaticArray" arraySize="1">
          <value>7</value>
        </property>
        <property name="approachRoute" type="String" container="StaticArray" arraySize="1">
          <value>lz_tent_I0000|rt_apr_tent_I_0000</value>
        </property>
        <property name="returnRoute" type="String" container="StaticArray" arraySize="1">
          <value>lz_tent_I0000|rt_rtn_tent_I_0000</value>
        </property>
      </staticProperties>
      <dynamicProperties />
    </entity>
    <entity class="TransformEntity" classVersion="0" addr="0x056BBD80" unknown1="80" unknown2="386865">
      <staticProperties>
        <property name="owner" type="EntityHandle" container="StaticArray" arraySize="1">
          <value>0x056BBD10</value>
        </property>
        <property name="transform_scale" type="Vector3" container="StaticArray" arraySize="1">
          <value x="0.999999166" y="1" z="0.999999166" w="1.121039E-44" />
        </property>
        <property name="transform_rotation_quat" type="Quat" container="StaticArray" arraySize="1">
          <value x="0" y="1" z="0" w="-8.344657E-07" />
        </property>
        <property name="transform_translation" type="Vector3" container="StaticArray" arraySize="1">
          <value x="-1761.735" y="310.6947" z="806.5125" w="1" />
        </property>
      </staticProperties>
      <dynamicProperties />
    </entity>
    <entity class="TppLandingZoneData" classVersion="1" addr="0x07BC5020" unknown1="272" unknown2="1169703">
      <staticProperties>
        <property name="name" type="String" container="StaticArray" arraySize="1">
          <value>lz_remnants_I0000|lz_remnants_I_0000</value>
        </property>
        <property name="dataSet" type="EntityHandle" container="StaticArray" arraySize="1">
          <value>0x07CDD050</value>
        </property>
        <property name="parent" type="EntityHandle" container="StaticArray" arraySize="1">
          <value>0x00000000</value>
        </property>
        <property name="transform" type="EntityPtr" container="StaticArray" arraySize="1">
          <value>0x07BC5090</value>
        </property>
        <property name="shearTransform" type="EntityPtr" container="StaticArray" arraySize="1">
          <value>0x00000000</value>
        </property>
        <property name="pivotTransform" type="EntityPtr" container="StaticArray" arraySize="1">
          <value>0x00000000</value>
        </property>
        <property name="children" type="EntityHandle" container="List" />
        <property name="flags" type="uint32" container="StaticArray" arraySize="1">
          <value>7</value>
        </property>
        <property name="approachRoute" type="String" container="StaticArray" arraySize="1">
          <value>lz_remnants_I0000|rt_apr_remnants_I_0000</value>
        </property>
        <property name="returnRoute" type="String" container="StaticArray" arraySize="1">
          <value>lz_remnants_I0000|rt_rtn_remnants_I_0000</value>
        </property>
      </staticProperties>
      <dynamicProperties />
    </entity>
    <entity class="TransformEntity" classVersion="0" addr="0x07BC5090" unknown1="80" unknown2="1169706">
      <staticProperties>
        <property name="owner" type="EntityHandle" container="StaticArray" arraySize="1">
          <value>0x07BC5020</value>
        </property>
        <property name="transform_scale" type="Vector3" container="StaticArray" arraySize="1">
          <value x="1.0000006" y="1" z="1.0000006" w="1.121039E-44" />
        </property>
        <property name="transform_rotation_quat" type="Quat" container="StaticArray" arraySize="1">
          <value x="0" y="-0.707106" z="0" w="0.707107544" />
        </property>
        <property name="transform_translation" type="Vector3" container="StaticArray" arraySize="1">
          <value x="-805.545" y="284.875" z="1820.651" w="1" />
        </property>
      </staticProperties>
      <dynamicProperties />
    </entity>
    <entity class="TppLandingZoneData" classVersion="1" addr="0x082598C0" unknown1="272" unknown2="41991331">
      <staticProperties>
        <property name="name" type="String" container="StaticArray" arraySize="1">
          <value>lz_tent_N0000|lz_tent_N_0000</value>
        </property>
        <property name="dataSet" type="EntityHandle" container="StaticArray" arraySize="1">
          <value>0x07CDD050</value>
        </property>
        <property name="parent" type="EntityHandle" container="StaticArray" arraySize="1">
          <value>0x00000000</value>
        </property>
        <property name="transform" type="EntityPtr" container="StaticArray" arraySize="1">
          <value>0x08259930</value>
        </property>
        <property name="shearTransform" type="EntityPtr" container="StaticArray" arraySize="1">
          <value>0x00000000</value>
        </property>
        <property name="pivotTransform" type="EntityPtr" container="StaticArray" arraySize="1">
          <value>0x00000000</value>
        </property>
        <property name="children" type="EntityHandle" container="List" />
        <property name="flags" type="uint32" container="StaticArray" arraySize="1">
          <value>7</value>
        </property>
        <property name="approachRoute" type="String" container="StaticArray" arraySize="1">
          <value>lz_tent_N0000|rt_apr_tent_N_0000</value>
        </property>
        <property name="returnRoute" type="String" container="StaticArray" arraySize="1">
          <value>lz_tent_N0000|rt_rtn_tent_N_0000</value>
        </property>
      </staticProperties>
      <dynamicProperties />
    </entity>
    <entity class="TransformEntity" classVersion="0" addr="0x08259930" unknown1="80" unknown2="41991334">
      <staticProperties>
        <property name="owner" type="EntityHandle" container="StaticArray" arraySize="1">
          <value>0x082598C0</value>
        </property>
        <property name="transform_scale" type="Vector3" container="StaticArray" arraySize="1">
          <value x="0.999998748" y="1" z="0.999998748" w="1.121039E-44" />
        </property>
        <property name="transform_rotation_quat" type="Quat" container="StaticArray" arraySize="1">
          <value x="0" y="0.79335016" z="0" w="0.608765662" />
        </property>
        <property name="transform_translation" type="Vector3" container="StaticArray" arraySize="1">
          <value x="-1868.779" y="331.483" z="538.7849" w="1" />
        </property>
      </staticProperties>
      <dynamicProperties />
    </entity>
    <entity class="TexturePackLoadConditioner" classVersion="0" addr="0x03FF5560" unknown1="72" unknown2="0">
      <staticProperties>
        <property name="name" type="String" container="StaticArray" arraySize="1">
          <value>TexturePackLoadConditioner0000</value>
        </property>
        <property name="dataSet" type="EntityHandle" container="StaticArray" arraySize="1">
          <value>0x07CDD050</value>
        </property>
        <property name="texturePackPath" type="Path" container="StaticArray" arraySize="1">
          <value hash="0xB8A0BF169F98" />
        </property>
      </staticProperties>
      <dynamicProperties />
    </entity>
  </entities>
</fox>